{
  "emotion_words": {
    "心动": {"body":["心跳漏拍加速","耳根发烫泛红","呼吸放轻"],"psych":["脑里炸开嗡嗡响只剩那张脸","目光被磁石吸住挪不开","胸腔揣了活物扑腾"],"action":["攥紧衣角指节发白","假装看手机屏幕亮了又灭","端杯喝水发觉是空的"],"env":["晚霞烧得正烈像泼翻橘色颜料","风铃叮当空气甜得发腻"]},
    "焦虑": {"body":["胃被攥住拧酸水涌","后背薄汗衬衫又冷又黏","太阳穴突突像针搅"],"psych":["最坏画面帧帧蹦刹不住","时钟每格像倒计时灾难","脑子转八件事全悬空"],"action":["指甲掐掌心月牙整齐","不停刷新页面","踱步鞋底磨亮地板砖"],"env":["荧光灯嗡嗡白得刺眼","安全出口绿光像警告"]},
    "崩溃": {"body":["泪不是涌是坍塌溢出","腿没力靠墙滑蹲地发抖","喉咙堵死哭声闷胸腔"],"psych":["支撑全断正在坠落没底","被掏空虚无连疼都感觉不到","千斤压太久断时没声响"],"action":["摔手机又捡捡了又摔","浴室角落花洒开衣服全湿","扒柜子东西翻一半跪在杂物中"],"env":["雨下得毫无章法像天发脾气","冰箱嗡鸣像心电监护仪"]},
    "愤怒": {"body":["太阳穴血管鼓青筋蜿蜒","牙关紧咬颌骨酸麻","血液煮沸胸腔烧到指尖"],"psych":["理智弦嘣断只剩凭什么","火气胃底蹿烧得眼前发白","不是生气是被背叛溺水"],"action":["拳攥又松松又攥关节响","扫文件到地散如白叶","猛站椅子滑半米刮出尖响"],"env":["灯管闪两下像也发怒","水杯被震晃泛不安涟漪"]},
    "恐惧": {"body":["后颈汗毛竖像被盯上","手脚冰凉指尖发麻","心脏猛缩像被无形手掐"],"psych":["大脑空白只剩念头尖叫跑","黑暗声响放大十倍每声像脚步","被黑暗一口口吞叫不出来"],"action":["后背贴墙一寸挪不敢眨眼","手指哆嗦摸开关按三次才亮","屏息连心跳声都觉得太响"],"env":["走廊灯忽明忽暗影子又长又扭","风从门缝挤呜呜叫像有人哭"]},
    "悲伤": {"body":["胸口压湿棉被沉得喘不上","眼眶酸胀鼻堵呼吸吞碎玻璃","身体抽骨软塌塌陷椅子里"],"psych":["世界调成灰色声音隔层水","不是撕裂是钝的慢的像涨潮","想起那人心空一块风灌进来"],"action":["抱衣服把脸埋闻散掉的味道","坐窗前发呆茶凉三遍没喝","翻聊天记录末句打了三字又删"],"env":["秋叶落窗台干枯卷曲像没寄的信","路灯把雨丝照成银针扎进夜色"]},
    "孤独": {"body":["缩沙发角抱成最小一团","揪袖口把毛衣揪出洞","满屋子人中间觉得被透明壳罩"],"psych":["不是没人是都隔毛玻璃看得见摸不着","通讯录翻三遍找不到说话的人","城市都在热闹她像弹出棋盘的棋子"],"action":["外卖备注打几行全删只写谢谢","开电视不看就为听个响","阳台抽烟看对面窗户一格格暗"],"env":["空走廊回荡自己脚步声像跟自己说话","冰箱白光照脸只有剩菜过期牛奶"]},
    "甜蜜": {"body":["嘴角不受控上翘咬唇压不住","心像浇热蜂蜜黏稠温热淌遍","呼吸变轻变柔怕吹散感觉"],"psych":["世界加柔光滤镜垃圾桶都顺眼","那人的字回放三遍每遍都甜","时间变慢想把这一刻摁住不让走"],"action":["截图存叫小确幸的相册","走路带弹跳鞋跟哒哒敲小曲","路过花店站很久买跟那天一样的花"],"env":["傍晚光蜂蜜色洒人行道像铺糖霜","小巷飘烤红薯甜香烟火气浓化不开"]},
    "压抑": {"body":["胸腔被铁箍箍住吸气觉得紧","喉咙堵像吞石头吐不出咽不下","后背绷铁板肩膀松不下来"],"psych":["情绪挤瓶子里盖拧死但能感觉晃","不能说不能喊不能哭出口全封死","表面风平底下暗流怕哪天决堤"],"action":["饭桌大家笑她也笑筷子戳半天没吃","深夜书桌笔尖按纸洇出墨点越来越大","打字又删删又打对话框停在输入状态"],"env":["天闷像扣锅气压低喘不上","房间没开灯窗帘严实黑暗稠得凝住"]},
    "绝望": {"body":["身体抽空连抬手都觉得重","眼睛干涩发疼已哭不出来","呼吸变浅变慢像身体自动关闭"],"psych":["所有出口试过每扇门后都是墙","希望一盏盏灭最后灭时反而平静","不期待好消息只求坏消息来时能站稳"],"action":["坐床边盯墙天亮到天黑姿势没变","未接来电全划掉一个没回","门反锁钥匙扔抽屉最深处"],"env":["天色灰蒙蒙分不清阴天傍晚时间停了","路灯坏一盏那段路黑着没人修"]},
    "释然": {"body":["肩膀猛松像卸掉扛久的担子","长呼一口气胸腔堵的跟着散","眼眶微热嘴角往上翘"],"psych":["绷久的弦终于松不是断是松","放下不是不在乎是终于跟自己和解","心里像退潮海滩礁石露出来粗粝踏实"],"action":["旧信叠好装箱放柜子最高层","走路突然停抬头看天继续走步子轻了","删掉收藏久的对话框手机轻了几克心也轻"],"env":["云层裂开一束光正好落脚边","风从敞开窗户吹窗帘鼓成弧度像叹息"]},
    "紧张": {"body":["手心沁薄汗擦不干","嗓子发紧咽口水费劲","小腿肌肉不自觉绷着"],"psych":["脑子转飞快但什么都抓不住像水里捞月亮","下一秒发生什么完全不知道","注意力拧成激光但射向虚无"],"action":["不停转笔转掉捡捡起来又转","面试前洗手间洗三遍水凉刺骨没感觉","简历翻来覆去看字都认识连一起读不进去"],"env":["候诊区钟走得特别慢秒针每格像嘲笑","考场笔尖划纸沙沙此起彼伏像蚕啃桑叶"]},
    "麻木": {"body":["整个人裹保鲜膜什么刺激隔一层","眼睛睁着没焦距什么没看进去","掐胳膊过两三秒才觉得疼"],"psych":["不是不难过是通道堵了情绪堆门口进不来","像出故障机器该哭没哭该笑没笑","悲伤太大身体保护机制关掉了感受"],"action":["公交过三站坐反方向也不换就那么坐着","别人叫名字叫三遍才慢慢转头眼神空空","冰箱过期一个月看了一眼又关门"],"env":["窗外下雪无声无息像世界按了静音","房间所有东西蒙薄灰像很久没人住"]},
    "嫉妒": {"body":["胃里泛酸像吞没熟青梅","嘴角维持微笑但咬肌绷得发疼","后槽牙咯吱响太阳穴跳疼"],"psych":["明知道不该比目光还是追着走每看一眼扎一下","酸意从胃底翻堵嗓子呼吸带涩味","恨的不是别人有的是自己连嫉妒资格都不配"],"action":["划手机越来越快什么都没看进去","笑着恭喜声音甜得自己都觉得假","回去对镜看很久刘海撩起来又放下"],"env":["橱窗模特穿当季新款笑容完美像一巴掌","路灯把影子拉很长跟别人怎么都重叠不到一起"]},
    "内疚": {"body":["胸口塞浸醋棉花又闷又酸","胃痉挛早饭堵那不上不下","后背像背看不见的石头肩膀沉下塌"],"psych":["反复回放画面每次同一节点卡住重来","那句话变刺扎喉咙咽不下去吐不出来","所有对不起堵嘴边知道说出来也没用"],"action":["不停搓手搓到关节发红像想搓掉脏东西","路过常去地方脚步慢想进又转身走","半夜坐起编辑长消息最后全删"],"env":["雨淅淅沥下一天像老天不放晴","日历圈起来的日期越来越近像倒计时炸弹"]},
    "狂喜": {"body":["眼泪笑声同时涌分不清哭笑","血液沸腾指尖发麻头皮过电酥","心脏擂得像要从嗓子眼蹦出来"],"psych":["不敢相信反复确认三遍才敢高兴","快乐从脚底冲天灵盖整个人发光","所有苦这一刻全兑了现值了全值了"],"action":["原地蹦鞋甩掉一只不管","抱旁边人转两圈脚离地","空旷地方跑起来张开双臂像要飞"],"env":["烟花头顶炸开碎光落下像下金色雨","阳光从云层后猛跳出来世界一秒亮了"]},
    "悔恨": {"body":["胃被从里往外翻恶心想干呕","指甲掐肉掌心半月印又深又红","像被抽巴掌脸上火辣但手是自己的"],"psych":["如果能回那瞬间愿用任何换重新选择","说出口收不回像泼的水在蒸发但水渍还在","后悔不是一阵是一辈子慢性病时不时发作"],"action":["反复翻那日期前后照片找错过的信号","在社交页面停很久连赞都不敢点","半夜突然坐起说没人听见的对不起"],"env":["秋叶被风卷起又落下像抓不住的时间","旧照片发黄卷边笑容还在但回不去了"]},
    "平静": {"body":["呼吸绵长均匀胸腔起伏小而稳","肩膀自然下垂后背靠椅背肌肉松弛","心跳慢而有力像远处寺庙钟声"],"psych":["心里湖终于静下来能看见湖底石头","什么都不想什么都不争此刻安宁是全部","暴风雨过海面平得像镜子倒映完整天"],"action":["泡茶看茶叶沉到杯底等水变温才喝","公园长椅看鸽子飞起来又落下来不赶时间","翻书到折角那页慢慢读困了合上睡"],"env":["午后阳光照木地板浮尘在光柱里缓缓游","远处传来钟声一声又一声间隔刚好够一次呼吸"]}
  },
  "environment": {
    "深夜卧室":{"at":["寂静","私密","暧昧"],"snd":["空调低嗡","远处偶尔车声"],"lit":["手机冷光映脸","窗帘缝漏路灯光弧线"],"sm":"被褥晒过太阳干燥气息","scene":"手机蓝光照亮半张脸被子拉到下巴翻身弹簧轻响窗帘缝路灯光在天花板画弧线像没尽头的桥"},
    "医院走廊":{"at":["冰冷","紧张","肃穆"],"snd":["心电监护滴声","护士站电话突兀响"],"lit":["惨白荧光灯消灭所有阴影","手术室红灯像不肯闭的眼"],"sm":"消毒水刺鼻混一丝药味","scene":"荧光灯照得没死角白墙白地白大褂像过度曝光照片手术室红灯亮着走廊尽头有人低声打电话声音被白色吞掉"},
    "雨天街头":{"at":["潮湿","落寞","黏稠"],"snd":["雨砸雨棚噼里啪啦","车轮碾积水哗啦"],"lit":["霓虹被雨幕打散成彩色雾","积水倒映红绿灯碎成流动颜料"],"sm":"泥土柏油被雨水翻出腥气","scene":"雨把街洗得发亮霓虹在积水碎成颜料伞下缩脖子快步走鞋踩水坑溅一裤腿谁也没抬头看谁"},
    "咖啡馆":{"at":["慵懒","温暖","松弛"],"snd":["咖啡机嘶嘶蒸汽","磨豆机短暂密集轰鸣"],"lit":["暖黄吊灯在木桌面洇开柔光","落地窗日光照进铺淡金色"],"sm":"咖啡豆烘焙焦香混牛奶甜","scene":"暖黄灯光从头顶落下咖啡拉花散了一半靠窗的人翻书翻页声很轻被咖啡机蒸汽盖过空气是焦糖和旧木头味"},
    "酒吧":{"at":["迷离","暧昧","躁动"],"snd":["冰块碰杯壁清脆","低音炮闷震胸腔"],"lit":["吧台射灯照酒杯通透琥珀像融宝石","角落蜡烛被空调吹摇摇晃"],"sm":"威士忌橡木桶气息混皮革沙发","scene":"低音炮闷震胸腔吧台射灯把威士忌照成融化琥珀调酒师甩雪克杯冰块哗啦碎酒液倒进杯像液态闪电"},
    "天台":{"at":["辽阔","孤绝","自由"],"snd":["风灌耳朵呼呼响","城市声音四面涌来又被风吹散"],"lit":["城市灯光脚下铺开像打翻一盒星星","月亮又圆又冷把水泥照泛白"],"sm":"风夹楼下排烟口飘上饭菜香","scene":"风很大头发吹乱整座城市脚下铺成光海远处高楼像发光柱子月亮冷冰冰水泥地有前人刻的字看不清了"},
    "地铁":{"at":["拥挤","疏离","疲惫"],"snd":["列车进站尖锐刹车","报站女声机械重复"],"lit":["车厢白光无影把每人脸照苍白","隧道灯一盏盏掠过明暗交替像翻胶片"],"sm":"人群混杂味香水汗味早餐包子搅一起","scene":"车厢挤得动不了所有人盯手机表情一模一样列车过隧道灯闪窗外只剩漆黑报站声响车门打开冷风灌进又关上"},
    "海边":{"at":["辽远","咸涩","自由"],"snd":["海浪一下下拍沙滩闷响","海鸥叫尖锐空旷"],"lit":["海面把阳光打碎成跳动光点","黄昏天海被染同一种橘粉分不清界限"],"sm":"海风咸腥混海藻腐烂味","scene":"海浪涌上来退下去把脚印抹干净海风吹头发黏脸上嘴唇是咸的远处天海连成线看久了分不清方向"},
    "办公室":{"at":["沉闷","压抑","机械"],"snd":["键盘此起彼伏像白噪音","打印机嗡嗡吐纸"],"lit":["日光灯照所有东西没温度","电脑光映眼镜片遮住眼神"],"sm":"中央空调干燥空气混打印纸油墨","scene":"日光灯亮一整天分不清外面白天黑夜键盘声此起彼伏打印机嗡嗡吐纸空调风吹眼睛发涩咖啡凉透了"},
    "老宅":{"at":["陈旧","沉寂","沧桑"],"snd":["木楼梯踩上去吱呀","老式挂钟沉闷滴答"],"lit":["阳光从雕花窗棂透进投斑驳影","灯泡昏黄暗淡只照亮中间一小片"],"sm":"老木头灰尘混一丝樟脑丸","scene":"推开木门灰尘在光柱翻涌老挂钟还在走滴答像房子心跳墙上照片泛黄照片里人笑着笑容也是黄的"}
  },
  "pacing_tech": {
    "短句紧张":{"ex":["他转身。门开着。没人。杯子还是热的。","她跑。鞋掉了不停。声音近了。拐弯。撞墙。没路了。"],"use":"追逐/悬疑揭晓/冲突爆发/生死关头"},
    "长句舒缓":{"ex":["阳光从最后一排窗户斜照进来在地板拉长光带浮尘在光柱旋转上升沉下像没目的地旅人。"],"use":"回忆/抒情/环境描写/情感沉淀"},
    "留白":{"ex":["她问你还好吗。他没回答。窗外树叶落了一片。","电话那头沉默很久。然后说我知道了。再然后挂断。"],"use":"告别/未说出口的话/情绪断裂点/余韵收束"},
    "蒙太奇":{"ex":["十八岁天台接吻。二十三岁民政局排队。二十八岁出租屋一个人吃泡面。电视开着没人看。"],"use":"时间跨度/对比揭示命运/多线并行/省略过程直击结果"},
    "时间压缩":{"ex":["那年春天他离开再回来巷口梧桐粗了一圈树下多了修鞋老头少了等他的人。"],"use":"岁月流逝/关系建立到崩塌/成长蜕变/物是人非"},
    "内心独白":{"ex":["我应该叫住她。应该跑过去。应该说点什么。但我没有。只是站原地看她背影越来越小。"],"use":"心理刻画/自我剖析/纠结挣扎/第一人称情感爆发"}
  },
  "sensory": {
    "视觉":[{"c":"看","a":"端详","e":"端详照片那张脸像辨认陌生人"},{"c":"亮","a":"刺目","e":"手术灯白得刺目什么都看不清"},{"c":"暗","a":"幽暗","e":"走廊尽头房间幽暗像张开的嘴"},{"c":"红","a":"殷红","e":"指尖划破殷红血珠慢慢沁出"},{"c":"白","a":"苍白","e":"她脸苍白像没用过的A4纸"},{"c":"黑","a":"漆黑","e":"停电四周漆黑连手指都看不见"},{"c":"美","a":"惊艳","e":"暮色里城市惊艳得不真实像过度修图的画"},{"c":"模糊","a":"朦胧","e":"晨雾小镇朦胧如梦房屋只露轮廓"}],
    "听觉":[{"c":"叫","a":"嘶吼","e":"电话那头嘶吼声音劈了像碎玻璃划铁板"},{"c":"说","a":"低喃","e":"他低喃一句声音被风吹走大半"},{"c":"哭","a":"呜咽","e":"脸埋枕头呜咽声闷闷像从水底传上来"},{"c":"安静","a":"沉寂","e":"枪响后整条街沉寂三秒然后尖叫炸开"},{"c":"笑","a":"嗤笑","e":"他嗤笑一声短促轻蔑像弹掉一粒灰"},{"c":"喊","a":"咆哮","e":"他咆哮着扫桌上东西声音在空房间来回弹"}],
    "触觉":[{"c":"冷","a":"冰冷","e":"手冰冷像刚从冰箱拿出来的鱼"},{"c":"热","a":"灼热","e":"发烧额头灼热像刚从烤箱取出的铁"},{"c":"摸","a":"摩挲","e":"摩挲戒指指腹感受凹凸刻字"},{"c":"粗","a":"粗粝","e":"手掌粗粝像砂纸握上来刮得手背发痒"},{"c":"痒","a":"酥麻","e":"气息喷在耳后酥麻顺脊柱窜下去"},{"c":"软","a":"绵软","e":"刚出炉面包绵软像云手指按就塌"}],
    "嗅觉":[{"c":"香","a":"馥郁","e":"桂花开了空气馥郁像泡在糖水里"},{"c":"闻","a":"嗅到","e":"嗅到一丝烟味从楼道飘上来若有若无"},{"c":"甜","a":"甜腻","e":"蛋糕房飘出甜腻味闻多了反胃"},{"c":"新鲜","a":"清新","e":"雨后空气清新像刚拆封深吸一口肺都凉"},{"c":"浓","a":"浓烈","e":"栀子花香浓烈几乎有实体黏空气化不开"},{"c":"淡","a":"若有若无","e":"那股若有若无的香水味靠近才闻得到"}],
    "味觉":[{"c":"甜","a":"甘甜","e":"山泉水入口甘甜像含化到一半的冰糖"},{"c":"苦","a":"苦涩","e":"黑咖啡苦涩在舌根蔓延久久不散"},{"c":"辣","a":"辛辣","e":"花椒辛辣从舌尖窜到后脑勺舌头像着火"},{"c":"咸","a":"咸涩","e":"眼泪流进嘴角咸涩的像海水"},{"c":"鲜","a":"鲜甜","e":"虾的鲜甜在舌尖化开不需要调味"},{"c":"香","a":"醇香","e":"老茶醇香在口腔慢慢展开像水墨画"}]
  }
}