{
  "characters": [
    {"name":"中二病","cat":"性格","s":["愚蠢的凡人","命运"],"e":["自我意识过剩","幻想掩饰自卑"],"g":["喜剧","校园"]},
    {"name":"二次元宅","cat":"性格","s":["awsl","DNA动了"],"e":["虚拟避风港","情感投射"],"g":["日常","校园"]},
    {"name":"二次元老婆","cat":"性格","s":["XX赛高","我推世界第一"],"e":["纸片人真爱","ACG表达"],"g":["日常","喜剧"]},
    {"name":"傻大姐","cat":"性格","s":["哈哈哈哈哈","又说错话"],"e":["大大咧咧","不记仇"],"g":["喜剧","日常"]},
    {"name":"傻白甜","cat":"性格","s":["真的吗","加油加油"],"e":["天真善良","信任碎了最痛"],"g":["恋爱","治愈"]},
    {"name":"养生女孩","cat":"性格","s":["多喝热水","湿气太重"],"e":["朋克养生矛盾","健康焦虑"],"g":["喜剧","日常"]},
    {"name":"冷血","cat":"性格","s":["嗯","无所谓","也许吧"],"e":["情感冻结","能感受不回应"],"g":["悬疑","暗黑"]},
    {"name":"变态","cat":"性格","s":["你是我的","嘻嘻"],"e":["甜蜜藏危险","极端占有"],"g":["恐怖","暗黑"]},
    {"name":"吃货","cat":"性格","s":["吃什么","好吃","绝了"],"e":["食物情绪调节","被投喂比告白感动"],"g":["日常","恋爱"]},
    {"name":"同事","cat":"性格","s":["一起搞定","辛苦了"],"e":["职场边界","竞合博弈"],"g":["职场"]},
    {"name":"嘴炮党","cat":"性格","s":["这次一定","快了快了"],"e":["说了等于做了","画饼满足"],"g":["喜剧","日常"]},
    {"name":"囤积癖","cat":"性格","s":["先放着","别扔"],"e":["物品记忆","分离焦虑"],"g":["日常","现实"]},
    {"name":"圣母","cat":"性格","s":["没关系","我帮你"],"e":["过度共情","拯救者情结"],"g":["治愈","虐心"]},
    {"name":"圣母婊","cat":"性格","s":["我为你好","你怎么不大度"],"e":["善良是武器","道德绑架"],"g":["暗黑","都市"]},
    {"name":"地雷妹","cat":"性格","s":["人家","你不喜欢我了"],"e":["甜时超甜炸时超炸","被抛弃恐惧"],"g":["恋爱","虐心"]},
    {"name":"夜猫子","cat":"性格","s":["再玩一会儿","今晚一定早睡"],"e":["报复性熬夜","私人时间补偿"],"g":["日常","都市"]},
    {"name":"女强人","cat":"性格","s":["结果导向","我来","不行"],"e":["果断高效","用成就证明"],"g":["职场","都市"]},
    {"name":"女拳","cat":"性格","s":["蝻","男人没好东西"],"e":["性别议题极端化"],"g":["都市"]},
    {"name":"女汉子","cat":"性格","s":["别磨叽","老娘"],"e":["外硬内软","不得不坚强"],"g":["日常","喜剧"]},
    {"name":"嫉妒狂","cat":"性格","s":["恭喜啊","真好"],"e":["表面祝福内心酸","比较消耗"],"g":["暗黑","都市"]},
    {"name":"学生党","cat":"性格","s":["DDL第一生产力","卷不动"],"e":["DDL驱动","焦虑自嘲"],"g":["校园","喜剧"]},
    {"name":"完美主义者","cat":"性格","s":["还可以更好","差不多不行"],"e":["永远不够好","焦虑驱动"],"g":["职场","日常"]},
    {"name":"小镇做题家","cat":"性格","s":["努力就好了"],"e":["自卑骄傲并存","阶层焦虑"],"g":["校园","现实"]},
    {"name":"工作狂","cat":"性格","s":["在忙","等忙完"],"e":["不工作就焦虑","价值绑定工作"],"g":["职场","都市"]},
    {"name":"平平无奇","cat":"性格","s":["还行吧","算了"],"e":["透明人感","不甘"],"g":["日常"]},
    {"name":"文风","cat":"性格","s":["今晚月色真美","怎么说呢"],"e":["诗意化世界","理想现实横跳"],"g":["文艺"]},
    {"name":"星座女孩","cat":"性格","s":["你什么星座","水逆"],"e":["用星座理解一切"],"g":["日常","喜剧"]},
    {"name":"杠精","cat":"性格","s":["不对","但是","你确定"],"e":["反射性反驳","找漏洞"],"g":["喜剧","都市"]},
    {"name":"死宅","cat":"性格","s":["好累嘛","不想出门"],"e":["社交回避","网络才是自己"],"g":["日常","喜剧"]},
    {"name":"没心没肺","cat":"性格","s":["有什么好想的","吃顿好的"],"e":["负面情绪滤网","自动漏掉"],"g":["喜剧","日常"]},
    {"name":"洁癖","cat":"性格","s":["你洗手了吗","擦一下"],"e":["对脏极度敏感","清洁仪式"],"g":["日常","喜剧"]},
    {"name":"渣女","cat":"性格","s":["你是最特别的","不想被束缚"],"e":["情感操控","征服快感"],"g":["恋爱","都市"]},
    {"name":"烂梗小鬼","cat":"性格","s":["家人们谁懂啊","YYDS"],"e":["万物皆可梗","背后孤独"],"g":["喜剧","日常"]},
    {"name":"独立女性","cat":"性格","s":["我自己来就好","一个人挺好"],"e":["三独立","不依附"],"g":["都市","职场"]},
    {"name":"猫奴","cat":"性格","s":["主子","铲屎官","好可爱"],"e":["猫是主子","等级分明"],"g":["日常","治愈"]},
    {"name":"玻璃心","cat":"性格","s":["对不起","可能是我想多了"],"e":["高敏感","情绪放大镜"],"g":["恋爱","虐心"]},
    {"name":"田园女权","cat":"性格","s":["凭什么","女生应被宠"],"e":["选择性权利"],"g":["都市"]},
    {"name":"病娇","cat":"性格","s":["你只能是我的","不会离开我"],"e":["甜蜜疯狂切换","极端偏执"],"g":["恐怖","暗黑","恋爱"]},
    {"name":"痴女","cat":"性格","s":["超级喜欢你"],"e":["大胆是伪装","缺爱是真相"],"g":["恋爱"]},
    {"name":"白莲花","cat":"性格","s":["我什么都没做","心机好深"],"e":["表面纯洁","内心深沉"],"g":["暗黑","都市"]},
    {"name":"社恐","cat":"性格","s":["嗯…不好意思","那个"],"e":["社交前焦虑中后反刍","渴望但恐惧"],"g":["日常","校园"]},
    {"name":"精神病","cat":"性格","s":["有趣","什么是正常"],"e":["超脱常规","不可预测"],"g":["恐怖","悬疑"]},
    {"name":"绿茶","cat":"性格","s":["人家不会嘛","你好厉害哦"],"e":["表面清纯","内心心机"],"g":["暗黑","恋爱"]},
    {"name":"绿茶婊","cat":"性格","s":["不是故意的嘛","都是我错"],"e":["表里不一","楚楚可怜武器"],"g":["暗黑"]},
    {"name":"缺爱","cat":"性格","s":["你爱我吗","再告诉我一遍"],"e":["情感黑洞","多少爱都不够"],"g":["恋爱","虐心"]},
    {"name":"老油条","cat":"性格","s":["不是我负责","当年我"],"e":["圆滑世故","精致利己"],"g":["职场","喜剧"]},
    {"name":"胆小鬼","cat":"性格","s":["不是不敢","心理建设"],"e":["什么都怕","灾难化播放"],"g":["日常","喜剧"]},
    {"name":"腹黑","cat":"性格","s":["你猜我在想什么","猜不到就对了"],"e":["表面温和","内心棋手"],"g":["悬疑","暗黑","职场"]},
    {"name":"行动派","cat":"性格","s":["先做了再说","直接做"],"e":["说了就做","完成大于完美"],"g":["职场","热血"]},
    {"name":"被害妄想","cat":"性格","s":["他是不是说我","肯定有目的"],"e":["恶意解读","信任缺失"],"g":["悬疑","日常"]},
    {"name":"被渣","cat":"性格","s":["我不信","又来了"],"e":["信任崩塌","防线过高"],"g":["恋爱","虐心"]},
    {"name":"讨好型人格","cat":"性格","s":["对不起都是我错","你开心就好"],"e":["害怕冲突","价值绑定他人"],"g":["日常","虐心"]},
    {"name":"话少","cat":"性格","s":["嗯","哦","行","不"],"e":["惜字如金","内心戏丰富"],"g":["日常","悬疑"]},
    {"name":"话痨","cat":"性格","s":["我跟你说","你绝对想不到"],"e":["用话填满空间","怕被忽略"],"g":["喜剧","日常"]},
    {"name":"败犬","cat":"性格","s":["你一定要幸福","我扛得住"],"e":["清醒赢不了","强颜欢笑"],"g":["恋爱","虐心"]},
    {"name":"购物狂","cat":"性格","s":["好便宜","不买亏了"],"e":["情绪驱动消费","多巴胺循环"],"g":["喜剧","都市"]},
    {"name":"跟踪狂","cat":"性格","s":["我只是关心TA"],"e":["病态执念","合理化能力强"],"g":["恐怖","暗黑"]},
    {"name":"跟风","cat":"性格","s":["大家都这么选"],"e":["从众安全感","缺独立思考"],"g":["日常"]},
    {"name":"路痴","cat":"性格","s":["我没迷路","不确定这是哪"],"e":["方向感为零","迷之自信"],"g":["喜剧","日常"]},
    {"name":"逻辑缜密","cat":"性格","s":["等一下线索有问题","第一第二第三"],"e":["细节控","证据链构建"],"g":["悬疑"]},
    {"name":"键盘侠","cat":"性格","s":["我说了真话","正义不会缺席"],"e":["线上线下人格分裂","匿名盔甲"],"g":["都市","喜剧"]},
    {"name":"强迫症","cat":"性格","s":["这个歪了","锁了吗"],"e":["秩序对称","检查循环"],"g":["日常","喜剧"]},
    {"name":"心机女","cat":"性格","s":["你猜呢"],"e":["城府极深","走一步看三步"],"g":["悬疑","暗黑","职场"]},
    {"name":"恋爱脑","cat":"性格","s":["他是我全世界","他怎么不回消息"],"e":["以对方为中心","焦虑依附"],"g":["恋爱","虐心"]},
    {"name":"恐婚族","cat":"性格","s":["不结婚也行","以后再说"],"e":["渴望亲密恐惧承诺"],"g":["日常","恋爱"]},
    {"name":"抑郁","cat":"性格","s":["我没事","嗯","哦"],"e":["持续低落","微笑面具"],"g":["现实","虐心"]},
    {"name":"拜金女","cat":"性格","s":["知道自己的价值"],"e":["物质即价值","安全感物质补偿"],"g":["都市","恋爱"]},
    {"name":"控制狂","cat":"性格","s":["听我的","只有我做才放心"],"e":["不安全感驱动","零容忍失控"],"g":["悬疑","暗黑"]},
    {"name":"搞笑女","cat":"性格","s":["自嘲段子随口"],"e":["幽默化解一切","搞笑背后脆弱"],"g":["喜剧","日常"]},
    {"name":"敏感多疑","cat":"性格","s":["你是不是不爱我"],"e":["威胁过度检测","安全感无底洞"],"g":["恋爱","虐心"]},
    {"name":"反驳型人格","cat":"性格","s":["不是","你逻辑有问题"],"e":["反射弧比大脑快"],"g":["喜剧","都市"]},
    {"name":"M性格","cat":"性格","s":["你说忍住那我就忍住"],"e":["痛感快感","臣服满足"],"g":["恋爱"]},
    {"name":"闷骚","cat":"性格","s":["我不是那种人"],"e":["嘴硬身体诚实"],"g":["恋爱","喜剧"]},
    {"name":"抖S","cat":"性格","s":["叫大声点","我允许你"],"e":["支配惩罚"],"g":["恋爱"]},
    {"name":"抖M","cat":"性格","s":["主人惩罚我吧"],"e":["服从讨好"],"g":["恋爱"]},
    {"name":"延迟症","cat":"性格","s":["再等五分钟"],"e":["慢热拖延"],"g":["喜剧","日常"]},
    {"name":"拖延症","cat":"性格","s":["明天吧","今天好累"],"e":["慢热拖延","逃避启动"],"g":["喜剧","日常"]},
    {"name":"社交恐惧","cat":"性格","s":["灯关了吗","别看我"],"e":["被看恐惧","身体暴露焦虑"],"g":["日常","恋爱"]}
  ]
}